SimpleThreading/__init__.py
ThreadDownloader2630.egg-info/PKG-INFO
ThreadDownloader2630.egg-info/SOURCES.txt
ThreadDownloader2630.egg-info/dependency_links.txt
ThreadDownloader2630.egg-info/top_level.txt