Metadata-Version: 1.0
Name: ThreadDownloader2630
Version: 1.0.0
Summary: MY first pythoon distribution
Home-page: UNKNOWN
Author: UNKNOWN
Author-email: UNKNOWN
License: UNKNOWN
Platform: UNKNOWN
